[
  {
    "name": "Agility",
    "image": "https://oldschool.runescape.wiki/images/8/86/Agility_icon.png?389e0",
    "emoji": "<:Agility:1332625012233994270>",
    "aliases": [
      "agility",
      "agil"
    ],
    "onlyShowBest": false,
    "caption": "1-25: Tourist trap quest or 5m\nPrice per marks of grace = 350k/ea (Canifis course or better required)\n+10% If you need marks collecting while training.",
    "methods": [
      {
        "title": "Best Method",
        "gpxp": 1064,
        "req": 1
      },
      {
        "title": "Best Method",
        "gpxp": 1015,
        "req": 20
      },
      {
        "title": "Best Method",
        "gpxp": 922,
        "req": 30
      },
      {
        "title": "Best Method",
        "gpxp": 935,
        "req": 40
      },
      {
        "title": "Best Method",
        "gpxp": 465,
        "req": 50
      },
      {
        "title": "Best Method",
        "gpxp": 250,
        "req": 60
      },
      {
        "title": "Best Methodt",
        "gpxp": 233,
        "req": 60
      },
      {
        "title": "Best Method",
        "gpxp": 233,
        "req": 70
      },
      {
        "title": "Best Method",
        "gpxp": 233,
        "req": 80
      },
      {
        "title": "Best Method",
        "gpxp": 233,
        "req": 80
      },
      {
        "title": "Best Method",
        "gpxp": 168,
        "req": 90
      }
    ]
  },
  {
    "name": "Construction",
    "image": "https://oldschool.runescape.wiki/images/f/f6/Construction_icon.png?f9bf7",
    "emoji": "<:Construction:1332625163862413324>",
    "aliases": [
      "construction",
      "con"
    ],
    "onlyShowBest": false,
    "caption": "Prices below for mahogany homes are per exp (gp/xp).\n25% If No Plank Sack.",
    "methods": [
      {
        "title": "Best Method",
        "gpxp": 250,
        "req": 1
      },
      {
        "title": "Oak Larders Without Butler",
        "gpxp": 227,
        "req": 33
      },
      {
        "title": "Mahogany Tables",
        "gpxp": 32,
        "req": 52
      },
      {
        "title": "Mahogany Homes",
        "gpxp": 202,
        "req": 50
      },
      {
        "title": "Mahogany Homes",
        "gpxp": 158,
        "req": 70
      }
    ]
  },
  {
    "name": "Cooking",
    "image": "https://oldschool.runescape.wiki/images/d/dc/Cooking_icon.png?a0156",
    "emoji": "<:Cooking:1332624838212456531>",
    "aliases": [
      "cooking",
      "cook"
    ],
    "onlyShowBest": false,
    "caption": "",
    "methods": [
      {
        "title": "Best Method",
        "gpxp": 100,
        "req": 1
      },
      {
        "title": "Wines",
        "gpxp": 26,
        "req": 35
      },
      {
        "title": "Cooking Fish With Cooking Gauntlets",
        "gpxp": 80,
        "req": 68
      }
    ]
  },
  {
    "name": "Crafting",
    "image": "https://oldschool.runescape.wiki/images/c/cf/Crafting_icon.png?a1f71",
    "emoji": "<:Crafting:1332624735888211988>",
    "aliases": [
      "crafting",
      "craft"
    ],
    "onlyShowBest": false,
    "methods": [
      {
        "title": "Best Method",
        "gpxp": 174,
        "req": 1
      },
      {
        "title": "Best Method",
        "gpxp": 174,
        "req": 46
      },
      {
        "title": "Best Method",
        "gpxp": 174,
        "req": 54
      },
      {
        "title": "Best Method",
        "gpxp": 42,
        "req": 63
      },
      {
        "title": "Best Method",
        "gpxp": 42,
        "req": 71
      },
      {
        "title": "Best Method",
        "gpxp": 43,
        "req": 77
      },
      {
        "title": "Best Method",
        "gpxp": 25,
        "req": 84
      },
      {
        "title": "Best Method",
        "gpxp": 25,
        "req": 90
      }
    ]
  },
  {
    "name": "Farming",
    "image": "https://oldschool.runescape.wiki/images/f/fc/Farming_icon.png?558fa",
    "emoji": "<:Farming:1332625141934456832>",
    "aliases": [
      "farming",
      "farm"
    ],
    "onlyShowBest": false,
    "caption": "+15% If No Teleport/Stamina",
    "methods": [
      {
        "title": "Best Tree Seeds",
        "gpxp": 341,
        "req": 1
      },
      {
        "title": "Tree Runs + Fruit Tree Runs",
        "gpxp": 121,
        "req": 45
      },
      {
        "title": "Tree Runs + Fruit Tree Runs",
        "gpxp": 30,
        "req": 75
      },
      {
        "title": " Tithe Farm Using Golovanova Seeds",
        "gpxp": 778,
        "req": 34
      },
      {
        "title": "Tithe Farm Using Bologano Seeds",
        "gpxp": 332,
        "req": 54
      },
      {
        "title": "Tithe Farm Using Logavano Seeds",
        "gpxp": 199,
        "req": 74
      }
    ]
  },
  {
    "name": "Firemaking",
    "image": "https://oldschool.runescape.wiki/images/9/9b/Firemaking_icon.png?45ea0",
    "emoji": "<:Firemaking:1332624860714893384>",
    "aliases": [
      "firemaking",
      "fm"
    ],
    "onlyShowBest": false,
    "caption": "Hcim Order +100%\n600k Per Crate",
    "methods": [
      {
        "title": "Best Method",
        "gpxp": 150,
        "req": 1
      },
      {
        "title": "Wintertodt",
        "gpxp": 50,
        "req": 50
      }
    ]
  },
  {
    "name": "Fishing",
    "image": "https://oldschool.runescape.wiki/images/3/3b/Fishing_icon.png?15a98",
    "emoji": "<:Fishing:1332624811293413386>",
    "aliases": [
      "fishing",
      "fish"
    ],
    "onlyShowBest": false,
    "caption": "",
    "methods": [
      {
        "title": "Best Method",
        "gpxp": 650,
        "req": 1
      },
      {
        "title": "Barb Fishing",
        "gpxp": 250,
        "req": 48
      },
      {
        "title": "Barb Fishing",
        "gpxp": 126,
        "req": 70
      },
      {
        "title": "Barb Fishing",
        "gpxp": 123,
        "req": 82
      },
      {
        "title": "Barb Fishing",
        "gpxp": 114,
        "req": 90
      }
    ]
  },
  {
    "name": "Fletching",
    "image": "https://oldschool.runescape.wiki/images/9/93/Fletching_icon.png?15cda",
    "emoji": "<:Fletching:1332625091032252481>",
    "aliases": [
      "fletching",
      "fletch"
    ],
    "onlyShowBest": false,
    "caption": "",
    "methods": [
      {
        "title": "Best Method",
        "gpxp": 20,
        "req": 1
      },
      {
        "title": "Best Method",
        "gpxp": 20,
        "req": 55
      },
      {
        "title": "broad arrows (just finishing the arrows)",
        "gpxp": 48,
        "req": 55
      },
      {
        "title": "broad arrows (from zero)",
        "gpxp": 96,
        "req": 55
      },
      {
        "title": "Best Method",
        "gpxp": 20,
        "req": 80,
        "caption": "You provide all supplies and keep all supplies/loot."
      },
      {
        "title": "broad arrows (just finishing the arrows)",
        "gpxp": 48,
        "req": 80
      },
      {
        "title": "broad arrows (from zero)",
        "gpxp": 96,
        "req": 80
      }
    ]
  },
  {
    "name": "Herblore",
    "image": "https://oldschool.runescape.wiki/images/0/03/Herblore_icon.png?ffa9e",
    "emoji": "<:Herblore:1332625035503992943>",
    "aliases": [
      "herblore",
      "herb"
    ],
    "onlyShowBest": false,
    "caption": "",
    "methods": [
      {
        "title": "Best Potion",
        "gpxp": 82,
        "req": 3
      },
      {
        "title": "Prayer Potion",
        "gpxp": 87,
        "req": 38
      },
      {
        "title": "Super Energy Potion",
        "gpxp": 43,
        "req": 52
      },
      {
        "title": "Super Restore Potion",
        "gpxp": 43,
        "req": 63
      },
      {
        "title": "Saradomin Brew",
        "gpxp": 31,
        "req": 81
      }
    ]
  },
  {
    "name": "Hunter",
    "image": "https://oldschool.runescape.wiki/images/d/dd/Hunter_icon.png?8762f",
    "emoji": "<:Hunter:1332625188289908808>",
    "aliases": [
      "hunter",
      "hunt",
      "hunting"
    ],
    "onlyShowBest": false,
    "caption": "",
    "methods": [
      {
        "title": "Best Method",
        "gpxp": 1496,
        "req": 1
      },
      {
        "title": "Swamp Lizards",
        "gpxp": 504,
        "req": 29
      },
      {
        "title": "Orange Salamanders",
        "gpxp": 469,
        "req": 47
      },
      {
        "title": "Red Salamanders",
        "gpxp": 194,
        "req": 59
      },
      {
        "title": "Monkey",
        "gpxp": 190,
        "req": 60
      },
      {
        "title": "Red chinchompas With Diary",
        "gpxp": 217,
        "req": 63
      },
      {
        "title": "Red chinchompas Without Diary",
        "gpxp": 262,
        "req": 63
      },
      {
        "title": "Black Salamanders",
        "gpxp": 168,
        "req": 67
      },
      {
        "title": "Red chinchompas Without Diary",
        "gpxp": 260,
        "req": 67
      },
      {
        "title": "Red chinchompas With Diary",
        "gpxp": 215,
        "req": 67
      },
      {
        "title": "Best Method",
        "gpxp": 169,
        "req": 73
      },
      {
        "title": "Red chinchompas Without Diary",
        "gpxp": 260,
        "req": 73
      },
      {
        "title": "Red chinchompas With Diary",
        "gpxp": 214,
        "req": 73
      },
      {
        "title": "Red chinchompas Without Diary",
        "gpxp": 195,
        "req": 80
      },
      {
        "title": "Red chinchompas With Diary",
        "gpxp": 177,
        "req": 80
      },
      {
        "title": "Red chinchompas Without Diary",
        "gpxp": 195,
        "req": 90
      },
      {
        "title": "Red chinchompas With Diary",
        "gpxp": 177,
        "req": 90
      }
    ]
  },
  {
    "name": "Magic",
    "image": "https://oldschool.runescape.wiki/images/5/5c/Magic_icon.png?334cf",
    "emoji": "<:Magic:1332624632930504766>",
    "aliases": [
      "magic",
      "mage"
    ],
    "onlyShowBest": false,
    "caption": "",
    "methods": [
      {
        "title": "Best Method",
        "gpxp": 124,
        "req": 1
      },
      {
        "title": "Best Method",
        "gpxp": 142,
        "req": 21
      },
      {
        "title": "Best Method",
        "gpxp": 109,
        "req": 55
      },
      {
        "title": "High Alchemy",
        "gpxp": 222,
        "req": 55
      },
      {
        "title": "Best Method",
        "gpxp": 97,
        "req": 65
      },
      {
        "title": "High Alchemy",
        "gpxp": 222,
        "req": 65
      },
      {
        "title": "Best Method",
        "gpxp": 70,
        "req": 70
      },
      {
        "title": "High Alchemy",
        "gpxp": 222,
        "req": 70
      },
      {
        "title": "Bursting (MM1)",
        "gpxp": 75,
        "req": 70,
        "caption": "HCIM +100%"
      },
      {
        "title": "Bursting (MM2)",
        "gpxp": 57,
        "req": 70,
        "caption": "HCIM +100%"
      },
      {
        "title": "Best Method",
        "gpxp": 67,
        "req": 94
      },
      {
        "title": "High Alchemy",
        "gpxp": 222,
        "req": 94
      },
      {
        "title": "Bursting (MM1)",
        "gpxp": 75,
        "req": 94,
        "caption": "HCIM +100%"
      },
      {
        "title": "Bursting (MM2)",
        "gpxp": 57,
        "req": 94,
        "caption": "HCIM +100%"
      }
    ]
  },
  {
    "name": "Melee",
    "image": "https://oldschool.runescape.wiki/images/Melee.png?0a53d",
    "emoji": "<:Strength:1332624310975856691>",
    "aliases": [
      "melee",
      "mains",
      "pures",
      "zerkers",
      "obby",
      "attack",
      "strength",
      "defence",
      "att",
      "str",
      "def"
    ],
    "onlyShowBest": false,
    "caption": "Blast furnace training is 5x normal price",
    "methods": [
      {
        "title": "Best Method",
        "gpxp": 493,
        "req": 1
      },
      {
        "title": "Sand Crabs - Mains",
        "gpxp": 62,
        "req": 50
      },
      {
        "title": "NMZ Prayer/Absorption - Mains",
        "gpxp": 41,
        "req": 50
      },
      {
        "title": "Sand Crabs - Pures/Zerkers",
        "gpxp": 94,
        "req": 50
      },
      {
        "title": "NMZ Prayer/Absorption",
        "gpxp": 43,
        "req": 70
      },
      {
        "title": "Sand Crabs",
        "gpxp": 62,
        "req": 70
      }
    ]
  },
  {
    "name": "Mining",
    "image": "https://oldschool.runescape.wiki/images/4/4a/Mining_icon.png?00870",
    "emoji": "<:Mining:1332624760089346140>",
    "aliases": [
      "mining",
      ""
    ],
    "onlyShowBest": false,
    "caption": "1-35: 12M (Set price)\n+25% Ironman If No D Pickaxe",
    "methods": [
      {
        "title": "Copper/Tin",
        "gpxp": 1451,
        "req": 1
      },
      {
        "title": "Iron Ore Power Mining",
        "gpxp": 800,
        "req": 15
      },
      {
        "title": "Motherlode (lower)",
        "gpxp": 375,
        "req": 35
      },
      {
        "title": "Motherlode (lower)",
        "gpxp": 305,
        "req": 72
      },
      {
        "title": "Motherlode Mine (Upper)",
        "gpxp": 179,
        "req": 72
      }
    ]
  },
  {
    "name": "Prayer",
    "image": "https://oldschool.runescape.wiki/images/f/f2/Prayer_icon.png?ca0dc",
    "emoji": "<:Prayer:1332624605621256232>",
    "aliases": [
      "prayer",
      "pray"
    ],
    "onlyShowBest": false,
    "caption": "",
    "methods": [
      {
        "title": "Best Method",
        "gpxp": 110,
        "req": 1
      },
      {
        "title": "Best Method",
        "gpxp": 130,
        "req": 16
      },
      {
        "title": "Best Method",
        "gpxp": 35,
        "req": 70
      }
    ]
  },
  {
    "name": "Ranged",
    "image": "https://oldschool.runescape.wiki/images/1/19/Ranged_icon.png?01b0e",
    "emoji": "<:Ranged:1332624576051679293>",
    "aliases": [
      "ranged",
      "range",
      "ranging"
    ],
    "onlyShowBest": false,
    "caption": "Prices May Vary Depending On Stats/Gear.",
    "methods": [
      {
        "title": "Sand Crabs Low Level",
        "gpxp": 130,
        "req": 1
      },
      {
        "title": "Sand Crabs Higher Level",
        "gpxp": 70,
        "req": 65
      },
      {
        "title": "Chinning - MM1",
        "gpxp": 60,
        "req": 65
      },
      {
        "title": "Chinning - MM2",
        "gpxp": 30,
        "req": 65
      },
      {
        "title": "Chinning - MM1",
        "gpxp": 60,
        "req": 90,
        "caption": "Hardcore +75%"
      },
      {
        "title": "Chinning - MM2",
        "gpxp": 30,
        "req": 90,
        "caption": "Hardcore +75%"
      }
    ]
  },
  {
    "name": "Runecrafting",
    "image": "https://oldschool.runescape.wiki/images/6/63/Runecraft_icon.png?c278c",
    "emoji": "<:Runecraft:1332624658767282198>",
    "aliases": [
      "runecrafting",
      "runecraft",
      "rc"
    ],
    "onlyShowBest": false,
    "caption": "If using Daeyalt Essence, the price is 20% cheaper",
    "methods": [
      {
        "title": "Library",
        "gpxp": 476,
        "req": 1
      },
      {
        "title": "Lava Runes",
        "gpxp": 463,
        "req": 23
      },
      {
        "title": "zmi",
        "gpxp": 320,
        "req": 50
      },
      {
        "title": "zmi",
        "gpxp": 271,
        "req": 77
      },
      {
        "title": "zeah Blood",
        "gpxp": 175,
        "req": 77
      },
      {
        "title": "zeah Soul",
        "gpxp": 153,
        "req": 90
      }
    ]
  },
  {
    "name": "Slayer",
    "image": "https://oldschool.runescape.wiki/images/2/28/Slayer_icon.png?cd34f",
    "emoji": "<:Slayer:1332625116181561426>",
    "aliases": [
      "slayer",
      "slay"
    ],
    "onlyShowBest": false,
    "caption": "No Bursting +10%\nKarluum Cave +15%\nNo Cannon +25%\nNo Prayer +25%\nIronman No Supplies +35%\nBoss Tasks +40%\nHardcore No Supplies +45%\nHardcore +100%",
    "methods": [
      {
        "title": "Main",
        "gpxp": 685,
        "req": 1
      },
      {
        "title": "Main 70-85 With High Tier Gear",
        "gpxp": 260,
        "req": 70
      },
      {
        "title": "Main 85+ With Top Tier Gear",
        "gpxp": 228,
        "req": 85
      },
      {
        "title": "Iron Below 70's With Low Tier Gear",
        "gpxp": 1163,
        "req": 1
      },
      {
        "title": "Iron 70-85 With High Tier Gear",
        "gpxp": 443,
        "req": 70
      },
      {
        "title": "Iron 85+ With Top Tier Gear",
        "gpxp": 389,
        "req": 85
      }
    ]
  },
  {
    "name": "Smithing",
    "image": "https://oldschool.runescape.wiki/images/d/dd/Smithing_icon.png?d26c5",
    "emoji": "<:Smithing:1332624784126906449>",
    "aliases": [
      "smithing",
      "smith"
    ],
    "onlyShowBest": false,
    "caption": "",
    "methods": [
      {
        "title": "Best Bars",
        "gpxp": 175,
        "req": 1
      },
      {
        "title": "Best Platebodies",
        "gpxp": 62,
        "req": 40
      },
      {
        "title": "blast furnace",
        "gpxp": 101,
        "req": 40
      }
    ]
  },
  {
    "name": "Thieving",
    "image": "https://oldschool.runescape.wiki/images/4/4a/Thieving_icon.png?973fe",
    "emoji": "<:Thieving:1332625059344416799>",
    "aliases": [
      "thieving",
      "thief"
    ],
    "onlyShowBest": false,
    "caption": "",
    "methods": [
      {
        "title": "Starter Method",
        "gpxp": 1147,
        "req": 1
      },
      {
        "title": "Fastest Method",
        "gpxp": 283,
        "req": 25
      },
      {
        "title": "Ardy Knights (55-75 Thieving) With Diary",
        "gpxp": 158,
        "req": 55
      },
      {
        "title": "Ardy Knights (75-95 Thieving) With Diary",
        "gpxp": 96,
        "req": 75
      },
      {
        "title": "Ardy Knights (95-99 Thieving) With Diary",
        "gpxp": 70,
        "req": 95
      }
    ]
  },
  {
    "name": "Woodcutting",
    "image": "https://oldschool.runescape.wiki/images/f/f4/Woodcutting_icon.png?6ead4",
    "emoji": "<:Woodcutting:1332624881959047181>",
    "aliases": [
      "woodcutting",
      "woodcut",
      "wc"
    ],
    "onlyShowBest": true,
    "caption": "",
    "methods": [
      {
        "title": "Starter Method Best Trees",
        "gpxp": 980,
        "req": 1
      },
      {
        "title": "Teak Trees",
        "gpxp": 133,
        "req": 35
      },
      {
        "title": "Redwood Trees",
        "gpxp": 99,
        "req": 90
      }
    ]
  }
]
